slskit/__init__.py
slskit/__main__.py
slskit/lib/__init__.py
slskit/lib/cli.py
slskit/lib/logging.py
slskit/opts.py
slskit/pillar.py
slskit/state.py
slskit/template.py
slskit/types.py
slskit-2025.3.0.dist-info/METADATA
slskit-2025.3.0.dist-info/WHEEL
slskit-2025.3.0.dist-info/entry_points.txt
slskit-2025.3.0.dist-info/RECORD
