Metadata-Version: 2.3
Name: slskit
Version: 2025.3.0
Summary: Tools for checking Salt state validity
Keywords: salt,saltstack,sls
Author: Gediminas Zlatkus
Author-email: gediminas.zlatkus@gmail.com
Requires-Python: >=3.9.2,<3.13
Classifier: Programming Language :: Python :: 3
Classifier: Programming Language :: Python :: 3.10
Classifier: Programming Language :: Python :: 3.11
Classifier: Programming Language :: Python :: 3.12
Classifier: Topic :: Software Development :: Quality Assurance
Requires-Dist: click
Requires-Dist: colorlog
Requires-Dist: funcy
Requires-Dist: jsonschema
Requires-Dist: salt (>=3006.0)
Project-URL: Homepage, https://github.com/gediminasz/slskit
Project-URL: Repository, https://github.com/gediminasz/slskit
